{"_path":"/estate-autunno-eventi","_dir":"","_draft":false,"_partial":false,"_locale":"","title":"Tra l'estate e l'autunno c'è sempre tanta roba!","description":"","date":"2016-09-04","tags":["eventi"],"draft":false,"summary":"Ora che Settembre è iniziato e domani ci sarà la prima vera settimana lavorativa dopo Agosto inizio a dare un'occhiata al calendario e segnarmi un po di cose, nella mia sfera di interessi è sempre un periodo pieno di cose interessanti!","images":["https://images.unsplash.com/photo-1506899686410-4670690fccef?ixid=MnwxMjA3fDB8MHxwaG90by1wYWdlfHx8fGVufDB8fHx8&ixlib=rb-1.2.1&auto=format&fit=crop&w=1200&q=80"],"readingTime":{"text":"3 min read","minutes":2.52,"time":151200,"words":504},"body":{"type":"root","children":[{"type":"element","tag":"script","props":{"async":true,"src":"//www.instagram.com/embed.js"},"children":[]},{"type":"element","tag":"p","props":{},"children":[{"type":"element","tag":"a","props":{"href":"https://unsplash.com/photos/Zl8zGdnNcP8","rel":["nofollow"]},"children":[{"type":"element","tag":"img","props":{"alt":"Foto di Aaron Burden su Unsplash","src":"https://images.unsplash.com/photo-1506899686410-4670690fccef?ixid=MnwxMjA3fDB8MHxwaG90by1wYWdlfHx8fGVufDB8fHx8&ixlib=rb-1.2.1&auto=format&fit=crop&w=1200&q=80"},"children":[]}]},{"type":"text","value":" "},{"type":"element","tag":"small","props":{},"children":[{"type":"element","tag":"em","props":{},"children":[{"type":"text","value":"Foto di Aaron Burden su Unsplash"}]}]}]},{"type":"element","tag":"p","props":{},"children":[{"type":"text","value":"Ora che Settembre è iniziato e domani ci sarà la prima vera settimana lavorativa dopo Agosto inizio a dare un'occhiata al calendario e segnarmi un po di cose, nella mia sfera di interessi è sempre un periodo pieno di cose interessanti!"}]},{"type":"element","tag":"h2","props":{"id":"festa-del-ticino-10-11-settembre-pavia"},"children":[{"type":"text","value":"Festa del Ticino "},{"type":"element","tag":"small","props":{},"children":[{"type":"text","value":"(10-11 Settembre, Pavia)"}]}]},{"type":"element","tag":"p","props":{},"children":[{"type":"text","value":"Per me l'"},{"type":"element","tag":"strong","props":{},"children":[{"type":"text","value":"estate finisce"}]},{"type":"text","value":" realmente con la Festa del Ticino di Pavia e lo spettacolo pirotecnico, di cui "},{"type":"element","tag":"a","props":{"href":"https://salvatorelaisa.blog/post/fuochi-fine-estate/","rel":["nofollow"]},"children":[{"type":"text","value":"ho già parlato in un post a parte"}]},{"type":"text","value":" quindi non mi ripeto, che quest'anno sarà il 10 Settembre."}]},{"type":"element","tag":"blockquote","props":{"className":["instagram-media"],"dataInstgrmCaptioned":"","dataInstgrmPermalink":"https://www.instagram.com/p/7TiCw2yVgC/?utm_source=ig_embed&utm_campaign=loading","dataInstgrmVersion":"14","style":" background:#FFF; border:0; border-radius:3px; box-shadow:0 0 1px 0 rgba(0,0,0,0.5),0 1px 10px 0 rgba(0,0,0,0.15); margin: 1px; max-width:540px; min-width:326px; padding:0; width:99.375%; width:-webkit-calc(100% - 2px); width:calc(100% - 2px);"},"children":[{"type":"element","tag":"div","props":{"style":"padding:16px;"},"children":[{"type":"text","value":" "},{"type":"element","tag":"a","props":{"href":"https://www.instagram.com/p/7TiCw2yVgC/?utm_source=ig_embed&utm_campaign=loading","style":" background:#FFFFFF; line-height:0; padding:0 0; text-align:center; text-decoration:none; width:100%;","target":"_blank"},"children":[{"type":"text","value":" "},{"type":"element","tag":"div","props":{"style":" display: flex; flex-direction: row; align-items: center;"},"children":[{"type":"text","value":" "},{"type":"element","tag":"div","props":{"style":"background-color: #F4F4F4; border-radius: 50%; flex-grow: 0; height: 40px; margin-right: 14px; width: 40px;"},"children":[]},{"type":"text","value":" "},{"type":"element","tag":"div","props":{"style":"display: flex; flex-direction: column; flex-grow: 1; justify-content: center;"},"children":[{"type":"text","value":" "},{"type":"element","tag":"div","props":{"style":" background-color: #F4F4F4; border-radius: 4px; flex-grow: 0; height: 14px; margin-bottom: 6px; width: 100px;"},"children":[]},{"type":"text","value":" "},{"type":"element","tag":"div","props":{"style":" background-color: #F4F4F4; border-radius: 4px; flex-grow: 0; height: 14px; width: 60px;"},"children":[]}]}]},{"type":"element","tag":"div","props":{"style":"padding: 19% 0;"},"children":[]},{"type":"text","value":" "},{"type":"element","tag":"div","props":{"style":"display:block; height:50px; margin:0 auto 12px; width:50px;"},"children":[{"type":"element","tag":"svg","props":{"width":"50px","height":"50px","viewBox":"0 0 60 60","version":"1.1","xmlns":"https://www.w3.org/2000/svg","xmlnsXLink":"https://www.w3.org/1999/xlink"},"children":[{"type":"element","tag":"g","props":{"stroke":"none","strokeWidth":"1","fill":"none","fillRule":"evenodd"},"children":[{"type":"element","tag":"g","props":{"transform":"translate(-511.000000, -20.000000)","fill":"#000000"},"children":[{"type":"element","tag":"g","props":{},"children":[{"type":"element","tag":"path","props":{"d":"M556.869,30.41 C554.814,30.41 553.148,32.076 553.148,34.131 C553.148,36.186 554.814,37.852 556.869,37.852 C558.924,37.852 560.59,36.186 560.59,34.131 C560.59,32.076 558.924,30.41 556.869,30.41 M541,60.657 C535.114,60.657 530.342,55.887 530.342,50 C530.342,44.114 535.114,39.342 541,39.342 C546.887,39.342 551.658,44.114 551.658,50 C551.658,55.887 546.887,60.657 541,60.657 M541,33.886 C532.1,33.886 524.886,41.1 524.886,50 C524.886,58.899 532.1,66.113 541,66.113 C549.9,66.113 557.115,58.899 557.115,50 C557.115,41.1 549.9,33.886 541,33.886 M565.378,62.101 C565.244,65.022 564.756,66.606 564.346,67.663 C563.803,69.06 563.154,70.057 562.106,71.106 C561.058,72.155 560.06,72.803 558.662,73.347 C557.607,73.757 556.021,74.244 553.102,74.378 C549.944,74.521 548.997,74.552 541,74.552 C533.003,74.552 532.056,74.521 528.898,74.378 C525.979,74.244 524.393,73.757 523.338,73.347 C521.94,72.803 520.942,72.155 519.894,71.106 C518.846,70.057 518.197,69.06 517.654,67.663 C517.244,66.606 516.755,65.022 516.623,62.101 C516.479,58.943 516.448,57.996 516.448,50 C516.448,42.003 516.479,41.056 516.623,37.899 C516.755,34.978 517.244,33.391 517.654,32.338 C518.197,30.938 518.846,29.942 519.894,28.894 C520.942,27.846 521.94,27.196 523.338,26.654 C524.393,26.244 525.979,25.756 528.898,25.623 C532.057,25.479 533.004,25.448 541,25.448 C548.997,25.448 549.943,25.479 553.102,25.623 C556.021,25.756 557.607,26.244 558.662,26.654 C560.06,27.196 561.058,27.846 562.106,28.894 C563.154,29.942 563.803,30.938 564.346,32.338 C564.756,33.391 565.244,34.978 565.378,37.899 C565.522,41.056 565.552,42.003 565.552,50 C565.552,57.996 565.522,58.943 565.378,62.101 M570.82,37.631 C570.674,34.438 570.167,32.258 569.425,30.349 C568.659,28.377 567.633,26.702 565.965,25.035 C564.297,23.368 562.623,22.342 560.652,21.575 C558.743,20.834 556.562,20.326 553.369,20.18 C550.169,20.033 549.148,20 541,20 C532.853,20 531.831,20.033 528.631,20.18 C525.438,20.326 523.257,20.834 521.349,21.575 C519.376,22.342 517.703,23.368 516.035,25.035 C514.368,26.702 513.342,28.377 512.574,30.349 C511.834,32.258 511.326,34.438 511.181,37.631 C511.035,40.831 511,41.851 511,50 C511,58.147 511.035,59.17 511.181,62.369 C511.326,65.562 511.834,67.743 512.574,69.651 C513.342,71.625 514.368,73.296 516.035,74.965 C517.703,76.634 519.376,77.658 521.349,78.425 C523.257,79.167 525.438,79.673 528.631,79.82 C531.831,79.965 532.853,80.001 541,80.001 C549.148,80.001 550.169,79.965 553.369,79.82 C556.562,79.673 558.743,79.167 560.652,78.425 C562.623,77.658 564.297,76.634 565.965,74.965 C567.633,73.296 568.659,71.625 569.425,69.651 C570.167,67.743 570.674,65.562 570.82,62.369 C570.966,59.17 571,58.147 571,50 C571,41.851 570.966,40.831 570.82,37.631"},"children":[]}]}]}]}]}]},{"type":"element","tag":"div","props":{"style":"padding-top: 8px;"},"children":[{"type":"text","value":" "},{"type":"element","tag":"div","props":{"style":" color:#3897f0; font-family:Arial,sans-serif; font-size:14px; font-style:normal; font-weight:550; line-height:18px;"},"children":[{"type":"text","value":"View this post on Instagram"}]}]},{"type":"element","tag":"div","props":{"style":"padding: 12.5% 0;"},"children":[]},{"type":"text","value":" "},{"type":"element","tag":"div","props":{"style":"display: flex; flex-direction: row; margin-bottom: 14px; align-items: center;"},"children":[{"type":"element","tag":"div","props":{},"children":[{"type":"text","value":" "},{"type":"element","tag":"div","props":{"style":"background-color: #F4F4F4; border-radius: 50%; height: 12.5px; width: 12.5px; transform: translateX(0px) translateY(7px);"},"children":[]},{"type":"text","value":" "},{"type":"element","tag":"div","props":{"style":"background-color: #F4F4F4; height: 12.5px; transform: rotate(-45deg) translateX(3px) translateY(1px); width: 12.5px; flex-grow: 0; margin-right: 14px; margin-left: 2px;"},"children":[]},{"type":"text","value":" "},{"type":"element","tag":"div","props":{"style":"background-color: #F4F4F4; border-radius: 50%; height: 12.5px; width: 12.5px; transform: translateX(9px) translateY(-18px);"},"children":[]}]},{"type":"element","tag":"div","props":{"style":"margin-left: 8px;"},"children":[{"type":"text","value":" "},{"type":"element","tag":"div","props":{"style":" background-color: #F4F4F4; border-radius: 50%; flex-grow: 0; height: 20px; width: 20px;"},"children":[]},{"type":"text","value":" "},{"type":"element","tag":"div","props":{"style":" width: 0; height: 0; border-top: 2px solid transparent; border-left: 6px solid #f4f4f4; border-bottom: 2px solid transparent; transform: translateX(16px) translateY(-4px) rotate(30deg)"},"children":[]}]},{"type":"element","tag":"div","props":{"style":"margin-left: auto;"},"children":[{"type":"text","value":" "},{"type":"element","tag":"div","props":{"style":" width: 0px; border-top: 8px solid #F4F4F4; border-right: 8px solid transparent; transform: translateY(16px);"},"children":[]},{"type":"text","value":" "},{"type":"element","tag":"div","props":{"style":" background-color: #F4F4F4; flex-grow: 0; height: 12px; width: 16px; transform: translateY(-4px);"},"children":[]},{"type":"text","value":" "},{"type":"element","tag":"div","props":{"style":" width: 0; height: 0; border-top: 8px solid #F4F4F4; border-left: 8px solid transparent; transform: translateY(-4px) translateX(8px);"},"children":[]}]}]},{"type":"text","value":" "},{"type":"element","tag":"div","props":{"style":"display: flex; flex-direction: column; flex-grow: 1; justify-content: center; margin-bottom: 24px;"},"children":[{"type":"text","value":" "},{"type":"element","tag":"div","props":{"style":" background-color: #F4F4F4; border-radius: 4px; flex-grow: 0; height: 14px; margin-bottom: 6px; width: 224px;"},"children":[]},{"type":"text","value":" "},{"type":"element","tag":"div","props":{"style":" background-color: #F4F4F4; border-radius: 4px; flex-grow: 0; height: 14px; width: 144px;"},"children":[]}]}]},{"type":"element","tag":"p","props":{"style":" color:#c9c8cd; font-family:Arial,sans-serif; font-size:14px; line-height:17px; margin-bottom:0; margin-top:8px; overflow:hidden; padding:8px 0 7px; text-align:center; text-overflow:ellipsis; white-space:nowrap;"},"children":[{"type":"element","tag":"a","props":{"href":"https://www.instagram.com/p/7TiCw2yVgC/?utm_source=ig_embed&utm_campaign=loading","style":" color:#c9c8cd; font-family:Arial,sans-serif; font-size:14px; font-style:normal; font-weight:normal; line-height:17px; text-decoration:none;","target":"_blank"},"children":[{"type":"text","value":"A post shared by Gianluca Barbetta (@lukeskybarbet)"}]}]}]}]},{"type":"element","tag":"h2","props":{"id":"autunno-pavese-23-26-settembre-pavia"},"children":[{"type":"text","value":"Autunno Pavese "},{"type":"element","tag":"small","props":{},"children":[{"type":"text","value":"(23-26 Settembre, Pavia)"}]}]},{"type":"element","tag":"p","props":{},"children":[{"type":"text","value":"Non è un "},{"type":"element","tag":"a","props":{"href":"http://www.autunnopavesedoc.it/","rel":["nofollow"]},"children":[{"type":"text","value":"evento"}]},{"type":"text","value":" a cui vado tutti gli anni, tendenzialmente è sempre uguale... ma da quando è stato spostato al Castello di Pavia sono più propenso a farci un giro se capita la sera e la compagnia giusta, "},{"type":"element","tag":"strong","props":{},"children":[{"type":"text","value":"risotto e vino"}]},{"type":"text","value":" a go-go!"}]},{"type":"element","tag":"blockquote","props":{"className":["instagram-media"],"dataInstgrmCaptioned":"","dataInstgrmPermalink":"https://www.instagram.com/p/8Gw_CFswPn/?utm_source=ig_embed&utm_campaign=loading","dataInstgrmVersion":"14","style":" background:#FFF; border:0; border-radius:3px; box-shadow:0 0 1px 0 rgba(0,0,0,0.5),0 1px 10px 0 rgba(0,0,0,0.15); margin: 1px; max-width:540px; min-width:326px; padding:0; width:99.375%; width:-webkit-calc(100% - 2px); width:calc(100% - 2px);"},"children":[{"type":"element","tag":"div","props":{"style":"padding:16px;"},"children":[{"type":"text","value":" "},{"type":"element","tag":"a","props":{"href":"https://www.instagram.com/p/8Gw_CFswPn/?utm_source=ig_embed&utm_campaign=loading","style":" background:#FFFFFF; line-height:0; padding:0 0; text-align:center; text-decoration:none; width:100%;","target":"_blank"},"children":[{"type":"text","value":" "},{"type":"element","tag":"div","props":{"style":" display: flex; flex-direction: row; align-items: center;"},"children":[{"type":"text","value":" "},{"type":"element","tag":"div","props":{"style":"background-color: #F4F4F4; border-radius: 50%; flex-grow: 0; height: 40px; margin-right: 14px; width: 40px;"},"children":[]},{"type":"text","value":" "},{"type":"element","tag":"div","props":{"style":"display: flex; flex-direction: column; flex-grow: 1; justify-content: center;"},"children":[{"type":"text","value":" "},{"type":"element","tag":"div","props":{"style":" background-color: #F4F4F4; border-radius: 4px; flex-grow: 0; height: 14px; margin-bottom: 6px; width: 100px;"},"children":[]},{"type":"text","value":" "},{"type":"element","tag":"div","props":{"style":" background-color: #F4F4F4; border-radius: 4px; flex-grow: 0; height: 14px; width: 60px;"},"children":[]}]}]},{"type":"element","tag":"div","props":{"style":"padding: 19% 0;"},"children":[]},{"type":"text","value":" "},{"type":"element","tag":"div","props":{"style":"display:block; height:50px; margin:0 auto 12px; width:50px;"},"children":[{"type":"element","tag":"svg","props":{"width":"50px","height":"50px","viewBox":"0 0 60 60","version":"1.1","xmlns":"https://www.w3.org/2000/svg","xmlnsXLink":"https://www.w3.org/1999/xlink"},"children":[{"type":"element","tag":"g","props":{"stroke":"none","strokeWidth":"1","fill":"none","fillRule":"evenodd"},"children":[{"type":"element","tag":"g","props":{"transform":"translate(-511.000000, -20.000000)","fill":"#000000"},"children":[{"type":"element","tag":"g","props":{},"children":[{"type":"element","tag":"path","props":{"d":"M556.869,30.41 C554.814,30.41 553.148,32.076 553.148,34.131 C553.148,36.186 554.814,37.852 556.869,37.852 C558.924,37.852 560.59,36.186 560.59,34.131 C560.59,32.076 558.924,30.41 556.869,30.41 M541,60.657 C535.114,60.657 530.342,55.887 530.342,50 C530.342,44.114 535.114,39.342 541,39.342 C546.887,39.342 551.658,44.114 551.658,50 C551.658,55.887 546.887,60.657 541,60.657 M541,33.886 C532.1,33.886 524.886,41.1 524.886,50 C524.886,58.899 532.1,66.113 541,66.113 C549.9,66.113 557.115,58.899 557.115,50 C557.115,41.1 549.9,33.886 541,33.886 M565.378,62.101 C565.244,65.022 564.756,66.606 564.346,67.663 C563.803,69.06 563.154,70.057 562.106,71.106 C561.058,72.155 560.06,72.803 558.662,73.347 C557.607,73.757 556.021,74.244 553.102,74.378 C549.944,74.521 548.997,74.552 541,74.552 C533.003,74.552 532.056,74.521 528.898,74.378 C525.979,74.244 524.393,73.757 523.338,73.347 C521.94,72.803 520.942,72.155 519.894,71.106 C518.846,70.057 518.197,69.06 517.654,67.663 C517.244,66.606 516.755,65.022 516.623,62.101 C516.479,58.943 516.448,57.996 516.448,50 C516.448,42.003 516.479,41.056 516.623,37.899 C516.755,34.978 517.244,33.391 517.654,32.338 C518.197,30.938 518.846,29.942 519.894,28.894 C520.942,27.846 521.94,27.196 523.338,26.654 C524.393,26.244 525.979,25.756 528.898,25.623 C532.057,25.479 533.004,25.448 541,25.448 C548.997,25.448 549.943,25.479 553.102,25.623 C556.021,25.756 557.607,26.244 558.662,26.654 C560.06,27.196 561.058,27.846 562.106,28.894 C563.154,29.942 563.803,30.938 564.346,32.338 C564.756,33.391 565.244,34.978 565.378,37.899 C565.522,41.056 565.552,42.003 565.552,50 C565.552,57.996 565.522,58.943 565.378,62.101 M570.82,37.631 C570.674,34.438 570.167,32.258 569.425,30.349 C568.659,28.377 567.633,26.702 565.965,25.035 C564.297,23.368 562.623,22.342 560.652,21.575 C558.743,20.834 556.562,20.326 553.369,20.18 C550.169,20.033 549.148,20 541,20 C532.853,20 531.831,20.033 528.631,20.18 C525.438,20.326 523.257,20.834 521.349,21.575 C519.376,22.342 517.703,23.368 516.035,25.035 C514.368,26.702 513.342,28.377 512.574,30.349 C511.834,32.258 511.326,34.438 511.181,37.631 C511.035,40.831 511,41.851 511,50 C511,58.147 511.035,59.17 511.181,62.369 C511.326,65.562 511.834,67.743 512.574,69.651 C513.342,71.625 514.368,73.296 516.035,74.965 C517.703,76.634 519.376,77.658 521.349,78.425 C523.257,79.167 525.438,79.673 528.631,79.82 C531.831,79.965 532.853,80.001 541,80.001 C549.148,80.001 550.169,79.965 553.369,79.82 C556.562,79.673 558.743,79.167 560.652,78.425 C562.623,77.658 564.297,76.634 565.965,74.965 C567.633,73.296 568.659,71.625 569.425,69.651 C570.167,67.743 570.674,65.562 570.82,62.369 C570.966,59.17 571,58.147 571,50 C571,41.851 570.966,40.831 570.82,37.631"},"children":[]}]}]}]}]}]},{"type":"element","tag":"div","props":{"style":"padding-top: 8px;"},"children":[{"type":"text","value":" "},{"type":"element","tag":"div","props":{"style":" color:#3897f0; font-family:Arial,sans-serif; font-size:14px; font-style:normal; font-weight:550; line-height:18px;"},"children":[{"type":"text","value":"View this post on Instagram"}]}]},{"type":"element","tag":"div","props":{"style":"padding: 12.5% 0;"},"children":[]},{"type":"text","value":" "},{"type":"element","tag":"div","props":{"style":"display: flex; flex-direction: row; margin-bottom: 14px; align-items: center;"},"children":[{"type":"element","tag":"div","props":{},"children":[{"type":"text","value":" "},{"type":"element","tag":"div","props":{"style":"background-color: #F4F4F4; border-radius: 50%; height: 12.5px; width: 12.5px; transform: translateX(0px) translateY(7px);"},"children":[]},{"type":"text","value":" "},{"type":"element","tag":"div","props":{"style":"background-color: #F4F4F4; height: 12.5px; transform: rotate(-45deg) translateX(3px) translateY(1px); width: 12.5px; flex-grow: 0; margin-right: 14px; margin-left: 2px;"},"children":[]},{"type":"text","value":" "},{"type":"element","tag":"div","props":{"style":"background-color: #F4F4F4; border-radius: 50%; height: 12.5px; width: 12.5px; transform: translateX(9px) translateY(-18px);"},"children":[]}]},{"type":"element","tag":"div","props":{"style":"margin-left: 8px;"},"children":[{"type":"text","value":" "},{"type":"element","tag":"div","props":{"style":" background-color: #F4F4F4; border-radius: 50%; flex-grow: 0; height: 20px; width: 20px;"},"children":[]},{"type":"text","value":" "},{"type":"element","tag":"div","props":{"style":" width: 0; height: 0; border-top: 2px solid transparent; border-left: 6px solid #f4f4f4; border-bottom: 2px solid transparent; transform: translateX(16px) translateY(-4px) rotate(30deg)"},"children":[]}]},{"type":"element","tag":"div","props":{"style":"margin-left: auto;"},"children":[{"type":"text","value":" "},{"type":"element","tag":"div","props":{"style":" width: 0px; border-top: 8px solid #F4F4F4; border-right: 8px solid transparent; transform: translateY(16px);"},"children":[]},{"type":"text","value":" "},{"type":"element","tag":"div","props":{"style":" background-color: #F4F4F4; flex-grow: 0; height: 12px; width: 16px; transform: translateY(-4px);"},"children":[]},{"type":"text","value":" "},{"type":"element","tag":"div","props":{"style":" width: 0; height: 0; border-top: 8px solid #F4F4F4; border-left: 8px solid transparent; transform: translateY(-4px) translateX(8px);"},"children":[]}]}]},{"type":"text","value":" "},{"type":"element","tag":"div","props":{"style":"display: flex; flex-direction: column; flex-grow: 1; justify-content: center; margin-bottom: 24px;"},"children":[{"type":"text","value":" "},{"type":"element","tag":"div","props":{"style":" background-color: #F4F4F4; border-radius: 4px; flex-grow: 0; height: 14px; margin-bottom: 6px; width: 224px;"},"children":[]},{"type":"text","value":" "},{"type":"element","tag":"div","props":{"style":" background-color: #F4F4F4; border-radius: 4px; flex-grow: 0; height: 14px; width: 144px;"},"children":[]}]}]},{"type":"element","tag":"p","props":{"style":" color:#c9c8cd; font-family:Arial,sans-serif; font-size:14px; line-height:17px; margin-bottom:0; margin-top:8px; overflow:hidden; padding:8px 0 7px; text-align:center; text-overflow:ellipsis; white-space:nowrap;"},"children":[{"type":"element","tag":"a","props":{"href":"https://www.instagram.com/p/8Gw_CFswPn/?utm_source=ig_embed&utm_campaign=loading","style":" color:#c9c8cd; font-family:Arial,sans-serif; font-size:14px; font-style:normal; font-weight:normal; line-height:17px; text-decoration:none;","target":"_blank"},"children":[{"type":"text","value":"A post shared by Avangart (@avangart_arte)"}]}]}]}]},{"type":"element","tag":"h2","props":{"id":"radiant-1-2-ottobre-novegro"},"children":[{"type":"text","value":"Radiant "},{"type":"element","tag":"small","props":{},"children":[{"type":"text","value":"(1-2 Ottobre, Novegro)"}]}]},{"type":"element","tag":"p","props":{},"children":[{"type":"text","value":"Anche di questo evento ne ho "},{"type":"element","tag":"a","props":{"href":"https://salvatorelaisa.blog/post/hdd-vs-cloud/","rel":["nofollow"]},"children":[{"type":"text","value":"più o meno già parlato in un altro post"}]},{"type":"text","value":". Non so se ci farò o un giro o meno, ma sapere che c'è è sempre una garanzia in più se proprio dovessi trovarmi senza nulla da fare e la voglia di buttare qualche soldo in cinesate "},{"type":"element","tag":"strong","props":{},"children":[{"type":"text","value":"tecnologiche"}]},{"type":"text","value":"."}]},{"type":"element","tag":"h2","props":{"id":"birrart-13-16-ottobre-casteggio"},"children":[{"type":"text","value":"BirrArt "},{"type":"element","tag":"small","props":{},"children":[{"type":"text","value":"(13-16 Ottobre, Casteggio)"}]}]},{"type":"element","tag":"p","props":{},"children":[{"type":"text","value":"Ormai sono "},{"type":"element","tag":"a","props":{"href":"http://www.birrart.org/","rel":["nofollow"]},"children":[{"type":"text","value":"8 anni"}]},{"type":"text","value":" che con questo evento Casteggio cerca di affiancare alla sua fama di città dei vini anche la "},{"type":"element","tag":"strong","props":{},"children":[{"type":"text","value":"birra"}]},{"type":"text","value":". Non nascondo che personalmente la fiera è molto meno di quello per cui viene spacciata, come qualità e offerta, ma mi piace considerarla l'ultima festa della birra prima dell'inverno."}]},{"type":"element","tag":"blockquote","props":{"className":["instagram-media"],"dataInstgrmCaptioned":"","dataInstgrmPermalink":"https://www.instagram.com/p/BDtpqshmuAV/?utm_source=ig_embed&utm_campaign=loading","dataInstgrmVersion":"14","style":" background:#FFF; border:0; border-radius:3px; box-shadow:0 0 1px 0 rgba(0,0,0,0.5),0 1px 10px 0 rgba(0,0,0,0.15); margin: 1px; max-width:540px; min-width:326px; padding:0; width:99.375%; width:-webkit-calc(100% - 2px); width:calc(100% - 2px);"},"children":[{"type":"element","tag":"div","props":{"style":"padding:16px;"},"children":[{"type":"text","value":" "},{"type":"element","tag":"a","props":{"href":"https://www.instagram.com/p/BDtpqshmuAV/?utm_source=ig_embed&utm_campaign=loading","style":" background:#FFFFFF; line-height:0; padding:0 0; text-align:center; text-decoration:none; width:100%;","target":"_blank"},"children":[{"type":"text","value":" "},{"type":"element","tag":"div","props":{"style":" display: flex; flex-direction: row; align-items: center;"},"children":[{"type":"text","value":" "},{"type":"element","tag":"div","props":{"style":"background-color: #F4F4F4; border-radius: 50%; flex-grow: 0; height: 40px; margin-right: 14px; width: 40px;"},"children":[]},{"type":"text","value":" "},{"type":"element","tag":"div","props":{"style":"display: flex; flex-direction: column; flex-grow: 1; justify-content: center;"},"children":[{"type":"text","value":" "},{"type":"element","tag":"div","props":{"style":" background-color: #F4F4F4; border-radius: 4px; flex-grow: 0; height: 14px; margin-bottom: 6px; width: 100px;"},"children":[]},{"type":"text","value":" "},{"type":"element","tag":"div","props":{"style":" background-color: #F4F4F4; border-radius: 4px; flex-grow: 0; height: 14px; width: 60px;"},"children":[]}]}]},{"type":"element","tag":"div","props":{"style":"padding: 19% 0;"},"children":[]},{"type":"text","value":" "},{"type":"element","tag":"div","props":{"style":"display:block; height:50px; margin:0 auto 12px; width:50px;"},"children":[{"type":"element","tag":"svg","props":{"width":"50px","height":"50px","viewBox":"0 0 60 60","version":"1.1","xmlns":"https://www.w3.org/2000/svg","xmlnsXLink":"https://www.w3.org/1999/xlink"},"children":[{"type":"element","tag":"g","props":{"stroke":"none","strokeWidth":"1","fill":"none","fillRule":"evenodd"},"children":[{"type":"element","tag":"g","props":{"transform":"translate(-511.000000, -20.000000)","fill":"#000000"},"children":[{"type":"element","tag":"g","props":{},"children":[{"type":"element","tag":"path","props":{"d":"M556.869,30.41 C554.814,30.41 553.148,32.076 553.148,34.131 C553.148,36.186 554.814,37.852 556.869,37.852 C558.924,37.852 560.59,36.186 560.59,34.131 C560.59,32.076 558.924,30.41 556.869,30.41 M541,60.657 C535.114,60.657 530.342,55.887 530.342,50 C530.342,44.114 535.114,39.342 541,39.342 C546.887,39.342 551.658,44.114 551.658,50 C551.658,55.887 546.887,60.657 541,60.657 M541,33.886 C532.1,33.886 524.886,41.1 524.886,50 C524.886,58.899 532.1,66.113 541,66.113 C549.9,66.113 557.115,58.899 557.115,50 C557.115,41.1 549.9,33.886 541,33.886 M565.378,62.101 C565.244,65.022 564.756,66.606 564.346,67.663 C563.803,69.06 563.154,70.057 562.106,71.106 C561.058,72.155 560.06,72.803 558.662,73.347 C557.607,73.757 556.021,74.244 553.102,74.378 C549.944,74.521 548.997,74.552 541,74.552 C533.003,74.552 532.056,74.521 528.898,74.378 C525.979,74.244 524.393,73.757 523.338,73.347 C521.94,72.803 520.942,72.155 519.894,71.106 C518.846,70.057 518.197,69.06 517.654,67.663 C517.244,66.606 516.755,65.022 516.623,62.101 C516.479,58.943 516.448,57.996 516.448,50 C516.448,42.003 516.479,41.056 516.623,37.899 C516.755,34.978 517.244,33.391 517.654,32.338 C518.197,30.938 518.846,29.942 519.894,28.894 C520.942,27.846 521.94,27.196 523.338,26.654 C524.393,26.244 525.979,25.756 528.898,25.623 C532.057,25.479 533.004,25.448 541,25.448 C548.997,25.448 549.943,25.479 553.102,25.623 C556.021,25.756 557.607,26.244 558.662,26.654 C560.06,27.196 561.058,27.846 562.106,28.894 C563.154,29.942 563.803,30.938 564.346,32.338 C564.756,33.391 565.244,34.978 565.378,37.899 C565.522,41.056 565.552,42.003 565.552,50 C565.552,57.996 565.522,58.943 565.378,62.101 M570.82,37.631 C570.674,34.438 570.167,32.258 569.425,30.349 C568.659,28.377 567.633,26.702 565.965,25.035 C564.297,23.368 562.623,22.342 560.652,21.575 C558.743,20.834 556.562,20.326 553.369,20.18 C550.169,20.033 549.148,20 541,20 C532.853,20 531.831,20.033 528.631,20.18 C525.438,20.326 523.257,20.834 521.349,21.575 C519.376,22.342 517.703,23.368 516.035,25.035 C514.368,26.702 513.342,28.377 512.574,30.349 C511.834,32.258 511.326,34.438 511.181,37.631 C511.035,40.831 511,41.851 511,50 C511,58.147 511.035,59.17 511.181,62.369 C511.326,65.562 511.834,67.743 512.574,69.651 C513.342,71.625 514.368,73.296 516.035,74.965 C517.703,76.634 519.376,77.658 521.349,78.425 C523.257,79.167 525.438,79.673 528.631,79.82 C531.831,79.965 532.853,80.001 541,80.001 C549.148,80.001 550.169,79.965 553.369,79.82 C556.562,79.673 558.743,79.167 560.652,78.425 C562.623,77.658 564.297,76.634 565.965,74.965 C567.633,73.296 568.659,71.625 569.425,69.651 C570.167,67.743 570.674,65.562 570.82,62.369 C570.966,59.17 571,58.147 571,50 C571,41.851 570.966,40.831 570.82,37.631"},"children":[]}]}]}]}]}]},{"type":"element","tag":"div","props":{"style":"padding-top: 8px;"},"children":[{"type":"text","value":" "},{"type":"element","tag":"div","props":{"style":" color:#3897f0; font-family:Arial,sans-serif; font-size:14px; font-style:normal; font-weight:550; line-height:18px;"},"children":[{"type":"text","value":"View this post on Instagram"}]}]},{"type":"element","tag":"div","props":{"style":"padding: 12.5% 0;"},"children":[]},{"type":"text","value":" "},{"type":"element","tag":"div","props":{"style":"display: flex; flex-direction: row; margin-bottom: 14px; align-items: center;"},"children":[{"type":"element","tag":"div","props":{},"children":[{"type":"text","value":" "},{"type":"element","tag":"div","props":{"style":"background-color: #F4F4F4; border-radius: 50%; height: 12.5px; width: 12.5px; transform: translateX(0px) translateY(7px);"},"children":[]},{"type":"text","value":" "},{"type":"element","tag":"div","props":{"style":"background-color: #F4F4F4; height: 12.5px; transform: rotate(-45deg) translateX(3px) translateY(1px); width: 12.5px; flex-grow: 0; margin-right: 14px; margin-left: 2px;"},"children":[]},{"type":"text","value":" "},{"type":"element","tag":"div","props":{"style":"background-color: #F4F4F4; border-radius: 50%; height: 12.5px; width: 12.5px; transform: translateX(9px) translateY(-18px);"},"children":[]}]},{"type":"element","tag":"div","props":{"style":"margin-left: 8px;"},"children":[{"type":"text","value":" "},{"type":"element","tag":"div","props":{"style":" background-color: #F4F4F4; border-radius: 50%; flex-grow: 0; height: 20px; width: 20px;"},"children":[]},{"type":"text","value":" "},{"type":"element","tag":"div","props":{"style":" width: 0; height: 0; border-top: 2px solid transparent; border-left: 6px solid #f4f4f4; border-bottom: 2px solid transparent; transform: translateX(16px) translateY(-4px) rotate(30deg)"},"children":[]}]},{"type":"element","tag":"div","props":{"style":"margin-left: auto;"},"children":[{"type":"text","value":" "},{"type":"element","tag":"div","props":{"style":" width: 0px; border-top: 8px solid #F4F4F4; border-right: 8px solid transparent; transform: translateY(16px);"},"children":[]},{"type":"text","value":" "},{"type":"element","tag":"div","props":{"style":" background-color: #F4F4F4; flex-grow: 0; height: 12px; width: 16px; transform: translateY(-4px);"},"children":[]},{"type":"text","value":" "},{"type":"element","tag":"div","props":{"style":" width: 0; height: 0; border-top: 8px solid #F4F4F4; border-left: 8px solid transparent; transform: translateY(-4px) translateX(8px);"},"children":[]}]}]},{"type":"text","value":" "},{"type":"element","tag":"div","props":{"style":"display: flex; flex-direction: column; flex-grow: 1; justify-content: center; margin-bottom: 24px;"},"children":[{"type":"text","value":" "},{"type":"element","tag":"div","props":{"style":" background-color: #F4F4F4; border-radius: 4px; flex-grow: 0; height: 14px; margin-bottom: 6px; width: 224px;"},"children":[]},{"type":"text","value":" "},{"type":"element","tag":"div","props":{"style":" background-color: #F4F4F4; border-radius: 4px; flex-grow: 0; height: 14px; width: 144px;"},"children":[]}]}]},{"type":"element","tag":"p","props":{"style":" color:#c9c8cd; font-family:Arial,sans-serif; font-size:14px; line-height:17px; margin-bottom:0; margin-top:8px; overflow:hidden; padding:8px 0 7px; text-align:center; text-overflow:ellipsis; white-space:nowrap;"},"children":[{"type":"element","tag":"a","props":{"href":"https://www.instagram.com/p/BDtpqshmuAV/?utm_source=ig_embed&utm_campaign=loading","style":" color:#c9c8cd; font-family:Arial,sans-serif; font-size:14px; font-style:normal; font-weight:normal; line-height:17px; text-decoration:none;","target":"_blank"},"children":[{"type":"text","value":"A post shared by Marianna ™ (@here.comes.mary)"}]}]}]}]},{"type":"element","tag":"h2","props":{"id":"games-week-14-16-ottobre-milano"},"children":[{"type":"text","value":"Games Week "},{"type":"element","tag":"small","props":{},"children":[{"type":"text","value":"(14-16 Ottobre, Milano)"}]}]},{"type":"element","tag":"p","props":{},"children":[{"type":"text","value":"Dopo aver passato alcuni anni tra la fine del '90 e l'inizio del 2000 a frequentare lo SMAU principalmente per vedere le "},{"type":"element","tag":"strong","props":{},"children":[{"type":"text","value":"novità videoludiche"}]},{"type":"text","value":", finalmente"},{"type":"element","tag":"a","props":{"href":"http://www.milangamesweek.it/","rel":["nofollow"]},"children":[{"type":"text","value":" una fiera dedicata solo a quelle"}]},{"type":"text","value":"! Occupando un solo padiglione della fiera di Milano, garantisce un giro completo degli stand con calma nel giro di un'oretta abbondante. Non mi metto mai a fare file per provare videogiochi in anteprima, si tratta di file di ore per titoli che usciranno breve, per me il vero forte sono gli angoli dedicati al "},{"type":"element","tag":"strong","props":{},"children":[{"type":"text","value":"retrogaming"}]},{"type":"text","value":" e gli sviluppatori indipendenti."}]},{"type":"element","tag":"blockquote","props":{"className":["instagram-media"],"dataInstgrmCaptioned":"","dataInstgrmPermalink":"https://www.instagram.com/p/BAft93twNIO/?utm_source=ig_embed&utm_campaign=loading","dataInstgrmVersion":"14","style":" background:#FFF; border:0; border-radius:3px; box-shadow:0 0 1px 0 rgba(0,0,0,0.5),0 1px 10px 0 rgba(0,0,0,0.15); margin: 1px; max-width:540px; min-width:326px; padding:0; width:99.375%; width:-webkit-calc(100% - 2px); width:calc(100% - 2px);"},"children":[{"type":"element","tag":"div","props":{"style":"padding:16px;"},"children":[{"type":"text","value":" "},{"type":"element","tag":"a","props":{"href":"https://www.instagram.com/p/BAft93twNIO/?utm_source=ig_embed&utm_campaign=loading","style":" background:#FFFFFF; line-height:0; padding:0 0; text-align:center; text-decoration:none; width:100%;","target":"_blank"},"children":[{"type":"text","value":" "},{"type":"element","tag":"div","props":{"style":" display: flex; flex-direction: row; align-items: center;"},"children":[{"type":"text","value":" "},{"type":"element","tag":"div","props":{"style":"background-color: #F4F4F4; border-radius: 50%; flex-grow: 0; height: 40px; margin-right: 14px; width: 40px;"},"children":[]},{"type":"text","value":" "},{"type":"element","tag":"div","props":{"style":"display: flex; flex-direction: column; flex-grow: 1; justify-content: center;"},"children":[{"type":"text","value":" "},{"type":"element","tag":"div","props":{"style":" background-color: #F4F4F4; border-radius: 4px; flex-grow: 0; height: 14px; margin-bottom: 6px; width: 100px;"},"children":[]},{"type":"text","value":" "},{"type":"element","tag":"div","props":{"style":" background-color: #F4F4F4; border-radius: 4px; flex-grow: 0; height: 14px; width: 60px;"},"children":[]}]}]},{"type":"element","tag":"div","props":{"style":"padding: 19% 0;"},"children":[]},{"type":"text","value":" "},{"type":"element","tag":"div","props":{"style":"display:block; height:50px; margin:0 auto 12px; width:50px;"},"children":[{"type":"element","tag":"svg","props":{"width":"50px","height":"50px","viewBox":"0 0 60 60","version":"1.1","xmlns":"https://www.w3.org/2000/svg","xmlnsXLink":"https://www.w3.org/1999/xlink"},"children":[{"type":"element","tag":"g","props":{"stroke":"none","strokeWidth":"1","fill":"none","fillRule":"evenodd"},"children":[{"type":"element","tag":"g","props":{"transform":"translate(-511.000000, -20.000000)","fill":"#000000"},"children":[{"type":"element","tag":"g","props":{},"children":[{"type":"element","tag":"path","props":{"d":"M556.869,30.41 C554.814,30.41 553.148,32.076 553.148,34.131 C553.148,36.186 554.814,37.852 556.869,37.852 C558.924,37.852 560.59,36.186 560.59,34.131 C560.59,32.076 558.924,30.41 556.869,30.41 M541,60.657 C535.114,60.657 530.342,55.887 530.342,50 C530.342,44.114 535.114,39.342 541,39.342 C546.887,39.342 551.658,44.114 551.658,50 C551.658,55.887 546.887,60.657 541,60.657 M541,33.886 C532.1,33.886 524.886,41.1 524.886,50 C524.886,58.899 532.1,66.113 541,66.113 C549.9,66.113 557.115,58.899 557.115,50 C557.115,41.1 549.9,33.886 541,33.886 M565.378,62.101 C565.244,65.022 564.756,66.606 564.346,67.663 C563.803,69.06 563.154,70.057 562.106,71.106 C561.058,72.155 560.06,72.803 558.662,73.347 C557.607,73.757 556.021,74.244 553.102,74.378 C549.944,74.521 548.997,74.552 541,74.552 C533.003,74.552 532.056,74.521 528.898,74.378 C525.979,74.244 524.393,73.757 523.338,73.347 C521.94,72.803 520.942,72.155 519.894,71.106 C518.846,70.057 518.197,69.06 517.654,67.663 C517.244,66.606 516.755,65.022 516.623,62.101 C516.479,58.943 516.448,57.996 516.448,50 C516.448,42.003 516.479,41.056 516.623,37.899 C516.755,34.978 517.244,33.391 517.654,32.338 C518.197,30.938 518.846,29.942 519.894,28.894 C520.942,27.846 521.94,27.196 523.338,26.654 C524.393,26.244 525.979,25.756 528.898,25.623 C532.057,25.479 533.004,25.448 541,25.448 C548.997,25.448 549.943,25.479 553.102,25.623 C556.021,25.756 557.607,26.244 558.662,26.654 C560.06,27.196 561.058,27.846 562.106,28.894 C563.154,29.942 563.803,30.938 564.346,32.338 C564.756,33.391 565.244,34.978 565.378,37.899 C565.522,41.056 565.552,42.003 565.552,50 C565.552,57.996 565.522,58.943 565.378,62.101 M570.82,37.631 C570.674,34.438 570.167,32.258 569.425,30.349 C568.659,28.377 567.633,26.702 565.965,25.035 C564.297,23.368 562.623,22.342 560.652,21.575 C558.743,20.834 556.562,20.326 553.369,20.18 C550.169,20.033 549.148,20 541,20 C532.853,20 531.831,20.033 528.631,20.18 C525.438,20.326 523.257,20.834 521.349,21.575 C519.376,22.342 517.703,23.368 516.035,25.035 C514.368,26.702 513.342,28.377 512.574,30.349 C511.834,32.258 511.326,34.438 511.181,37.631 C511.035,40.831 511,41.851 511,50 C511,58.147 511.035,59.17 511.181,62.369 C511.326,65.562 511.834,67.743 512.574,69.651 C513.342,71.625 514.368,73.296 516.035,74.965 C517.703,76.634 519.376,77.658 521.349,78.425 C523.257,79.167 525.438,79.673 528.631,79.82 C531.831,79.965 532.853,80.001 541,80.001 C549.148,80.001 550.169,79.965 553.369,79.82 C556.562,79.673 558.743,79.167 560.652,78.425 C562.623,77.658 564.297,76.634 565.965,74.965 C567.633,73.296 568.659,71.625 569.425,69.651 C570.167,67.743 570.674,65.562 570.82,62.369 C570.966,59.17 571,58.147 571,50 C571,41.851 570.966,40.831 570.82,37.631"},"children":[]}]}]}]}]}]},{"type":"element","tag":"div","props":{"style":"padding-top: 8px;"},"children":[{"type":"text","value":" "},{"type":"element","tag":"div","props":{"style":" color:#3897f0; font-family:Arial,sans-serif; font-size:14px; font-style:normal; font-weight:550; line-height:18px;"},"children":[{"type":"text","value":"View this post on Instagram"}]}]},{"type":"element","tag":"div","props":{"style":"padding: 12.5% 0;"},"children":[]},{"type":"text","value":" "},{"type":"element","tag":"div","props":{"style":"display: flex; flex-direction: row; margin-bottom: 14px; align-items: center;"},"children":[{"type":"element","tag":"div","props":{},"children":[{"type":"text","value":" "},{"type":"element","tag":"div","props":{"style":"background-color: #F4F4F4; border-radius: 50%; height: 12.5px; width: 12.5px; transform: translateX(0px) translateY(7px);"},"children":[]},{"type":"text","value":" "},{"type":"element","tag":"div","props":{"style":"background-color: #F4F4F4; height: 12.5px; transform: rotate(-45deg) translateX(3px) translateY(1px); width: 12.5px; flex-grow: 0; margin-right: 14px; margin-left: 2px;"},"children":[]},{"type":"text","value":" "},{"type":"element","tag":"div","props":{"style":"background-color: #F4F4F4; border-radius: 50%; height: 12.5px; width: 12.5px; transform: translateX(9px) translateY(-18px);"},"children":[]}]},{"type":"element","tag":"div","props":{"style":"margin-left: 8px;"},"children":[{"type":"text","value":" "},{"type":"element","tag":"div","props":{"style":" background-color: #F4F4F4; border-radius: 50%; flex-grow: 0; height: 20px; width: 20px;"},"children":[]},{"type":"text","value":" "},{"type":"element","tag":"div","props":{"style":" width: 0; height: 0; border-top: 2px solid transparent; border-left: 6px solid #f4f4f4; border-bottom: 2px solid transparent; transform: translateX(16px) translateY(-4px) rotate(30deg)"},"children":[]}]},{"type":"element","tag":"div","props":{"style":"margin-left: auto;"},"children":[{"type":"text","value":" "},{"type":"element","tag":"div","props":{"style":" width: 0px; border-top: 8px solid #F4F4F4; border-right: 8px solid transparent; transform: translateY(16px);"},"children":[]},{"type":"text","value":" "},{"type":"element","tag":"div","props":{"style":" background-color: #F4F4F4; flex-grow: 0; height: 12px; width: 16px; transform: translateY(-4px);"},"children":[]},{"type":"text","value":" "},{"type":"element","tag":"div","props":{"style":" width: 0; height: 0; border-top: 8px solid #F4F4F4; border-left: 8px solid transparent; transform: translateY(-4px) translateX(8px);"},"children":[]}]}]},{"type":"text","value":" "},{"type":"element","tag":"div","props":{"style":"display: flex; flex-direction: column; flex-grow: 1; justify-content: center; margin-bottom: 24px;"},"children":[{"type":"text","value":" "},{"type":"element","tag":"div","props":{"style":" background-color: #F4F4F4; border-radius: 4px; flex-grow: 0; height: 14px; margin-bottom: 6px; width: 224px;"},"children":[]},{"type":"text","value":" "},{"type":"element","tag":"div","props":{"style":" background-color: #F4F4F4; border-radius: 4px; flex-grow: 0; height: 14px; width: 144px;"},"children":[]}]}]},{"type":"element","tag":"p","props":{"style":" color:#c9c8cd; font-family:Arial,sans-serif; font-size:14px; line-height:17px; margin-bottom:0; margin-top:8px; overflow:hidden; padding:8px 0 7px; text-align:center; text-overflow:ellipsis; white-space:nowrap;"},"children":[{"type":"element","tag":"a","props":{"href":"https://www.instagram.com/p/BAft93twNIO/?utm_source=ig_embed&utm_campaign=loading","style":" color:#c9c8cd; font-family:Arial,sans-serif; font-size:14px; font-style:normal; font-weight:normal; line-height:17px; text-decoration:none;","target":"_blank"},"children":[{"type":"text","value":"A post shared by Andrea Arwain Caleo (@caleo_andrea)"}]}]}]}]},{"type":"element","tag":"h2","props":{"id":"next-vintage-14-17-ottobre-belgioioso"},"children":[{"type":"text","value":"Next Vintage "},{"type":"element","tag":"small","props":{},"children":[{"type":"text","value":"(14-17 Ottobre, Belgioioso)"}]}]},{"type":"element","tag":"p","props":{},"children":[{"type":"text","value":"Il castello di Belgioioso è sempre un'ottima cornice per eventi, e il Next Vintage è un'occasione per sbirciare tra cinafrusaglie degli anni 60/70, anche se la mostra è principalmente centrata su abbigliamento, ogni tanto qualche chicca salta fuori."}]},{"type":"element","tag":"blockquote","props":{"className":["instagram-media"],"dataInstgrmCaptioned":"","dataInstgrmPermalink":"https://www.instagram.com/p/88DiuyPmdl/?utm_source=ig_embed&utm_campaign=loading","dataInstgrmVersion":"14","style":" background:#FFF; border:0; border-radius:3px; box-shadow:0 0 1px 0 rgba(0,0,0,0.5),0 1px 10px 0 rgba(0,0,0,0.15); margin: 1px; max-width:540px; min-width:326px; padding:0; width:99.375%; width:-webkit-calc(100% - 2px); width:calc(100% - 2px);"},"children":[{"type":"element","tag":"div","props":{"style":"padding:16px;"},"children":[{"type":"text","value":" "},{"type":"element","tag":"a","props":{"href":"https://www.instagram.com/p/88DiuyPmdl/?utm_source=ig_embed&utm_campaign=loading","style":" background:#FFFFFF; line-height:0; padding:0 0; text-align:center; text-decoration:none; width:100%;","target":"_blank"},"children":[{"type":"text","value":" "},{"type":"element","tag":"div","props":{"style":" display: flex; flex-direction: row; align-items: center;"},"children":[{"type":"text","value":" "},{"type":"element","tag":"div","props":{"style":"background-color: #F4F4F4; border-radius: 50%; flex-grow: 0; height: 40px; margin-right: 14px; width: 40px;"},"children":[]},{"type":"text","value":" "},{"type":"element","tag":"div","props":{"style":"display: flex; flex-direction: column; flex-grow: 1; justify-content: center;"},"children":[{"type":"text","value":" "},{"type":"element","tag":"div","props":{"style":" background-color: #F4F4F4; border-radius: 4px; flex-grow: 0; height: 14px; margin-bottom: 6px; width: 100px;"},"children":[]},{"type":"text","value":" "},{"type":"element","tag":"div","props":{"style":" background-color: #F4F4F4; border-radius: 4px; flex-grow: 0; height: 14px; width: 60px;"},"children":[]}]}]},{"type":"element","tag":"div","props":{"style":"padding: 19% 0;"},"children":[]},{"type":"text","value":" "},{"type":"element","tag":"div","props":{"style":"display:block; height:50px; margin:0 auto 12px; width:50px;"},"children":[{"type":"element","tag":"svg","props":{"width":"50px","height":"50px","viewBox":"0 0 60 60","version":"1.1","xmlns":"https://www.w3.org/2000/svg","xmlnsXLink":"https://www.w3.org/1999/xlink"},"children":[{"type":"element","tag":"g","props":{"stroke":"none","strokeWidth":"1","fill":"none","fillRule":"evenodd"},"children":[{"type":"element","tag":"g","props":{"transform":"translate(-511.000000, -20.000000)","fill":"#000000"},"children":[{"type":"element","tag":"g","props":{},"children":[{"type":"element","tag":"path","props":{"d":"M556.869,30.41 C554.814,30.41 553.148,32.076 553.148,34.131 C553.148,36.186 554.814,37.852 556.869,37.852 C558.924,37.852 560.59,36.186 560.59,34.131 C560.59,32.076 558.924,30.41 556.869,30.41 M541,60.657 C535.114,60.657 530.342,55.887 530.342,50 C530.342,44.114 535.114,39.342 541,39.342 C546.887,39.342 551.658,44.114 551.658,50 C551.658,55.887 546.887,60.657 541,60.657 M541,33.886 C532.1,33.886 524.886,41.1 524.886,50 C524.886,58.899 532.1,66.113 541,66.113 C549.9,66.113 557.115,58.899 557.115,50 C557.115,41.1 549.9,33.886 541,33.886 M565.378,62.101 C565.244,65.022 564.756,66.606 564.346,67.663 C563.803,69.06 563.154,70.057 562.106,71.106 C561.058,72.155 560.06,72.803 558.662,73.347 C557.607,73.757 556.021,74.244 553.102,74.378 C549.944,74.521 548.997,74.552 541,74.552 C533.003,74.552 532.056,74.521 528.898,74.378 C525.979,74.244 524.393,73.757 523.338,73.347 C521.94,72.803 520.942,72.155 519.894,71.106 C518.846,70.057 518.197,69.06 517.654,67.663 C517.244,66.606 516.755,65.022 516.623,62.101 C516.479,58.943 516.448,57.996 516.448,50 C516.448,42.003 516.479,41.056 516.623,37.899 C516.755,34.978 517.244,33.391 517.654,32.338 C518.197,30.938 518.846,29.942 519.894,28.894 C520.942,27.846 521.94,27.196 523.338,26.654 C524.393,26.244 525.979,25.756 528.898,25.623 C532.057,25.479 533.004,25.448 541,25.448 C548.997,25.448 549.943,25.479 553.102,25.623 C556.021,25.756 557.607,26.244 558.662,26.654 C560.06,27.196 561.058,27.846 562.106,28.894 C563.154,29.942 563.803,30.938 564.346,32.338 C564.756,33.391 565.244,34.978 565.378,37.899 C565.522,41.056 565.552,42.003 565.552,50 C565.552,57.996 565.522,58.943 565.378,62.101 M570.82,37.631 C570.674,34.438 570.167,32.258 569.425,30.349 C568.659,28.377 567.633,26.702 565.965,25.035 C564.297,23.368 562.623,22.342 560.652,21.575 C558.743,20.834 556.562,20.326 553.369,20.18 C550.169,20.033 549.148,20 541,20 C532.853,20 531.831,20.033 528.631,20.18 C525.438,20.326 523.257,20.834 521.349,21.575 C519.376,22.342 517.703,23.368 516.035,25.035 C514.368,26.702 513.342,28.377 512.574,30.349 C511.834,32.258 511.326,34.438 511.181,37.631 C511.035,40.831 511,41.851 511,50 C511,58.147 511.035,59.17 511.181,62.369 C511.326,65.562 511.834,67.743 512.574,69.651 C513.342,71.625 514.368,73.296 516.035,74.965 C517.703,76.634 519.376,77.658 521.349,78.425 C523.257,79.167 525.438,79.673 528.631,79.82 C531.831,79.965 532.853,80.001 541,80.001 C549.148,80.001 550.169,79.965 553.369,79.82 C556.562,79.673 558.743,79.167 560.652,78.425 C562.623,77.658 564.297,76.634 565.965,74.965 C567.633,73.296 568.659,71.625 569.425,69.651 C570.167,67.743 570.674,65.562 570.82,62.369 C570.966,59.17 571,58.147 571,50 C571,41.851 570.966,40.831 570.82,37.631"},"children":[]}]}]}]}]}]},{"type":"element","tag":"div","props":{"style":"padding-top: 8px;"},"children":[{"type":"text","value":" "},{"type":"element","tag":"div","props":{"style":" color:#3897f0; font-family:Arial,sans-serif; font-size:14px; font-style:normal; font-weight:550; line-height:18px;"},"children":[{"type":"text","value":"View this post on Instagram"}]}]},{"type":"element","tag":"div","props":{"style":"padding: 12.5% 0;"},"children":[]},{"type":"text","value":" "},{"type":"element","tag":"div","props":{"style":"display: flex; flex-direction: row; margin-bottom: 14px; align-items: center;"},"children":[{"type":"element","tag":"div","props":{},"children":[{"type":"text","value":" "},{"type":"element","tag":"div","props":{"style":"background-color: #F4F4F4; border-radius: 50%; height: 12.5px; width: 12.5px; transform: translateX(0px) translateY(7px);"},"children":[]},{"type":"text","value":" "},{"type":"element","tag":"div","props":{"style":"background-color: #F4F4F4; height: 12.5px; transform: rotate(-45deg) translateX(3px) translateY(1px); width: 12.5px; flex-grow: 0; margin-right: 14px; margin-left: 2px;"},"children":[]},{"type":"text","value":" "},{"type":"element","tag":"div","props":{"style":"background-color: #F4F4F4; border-radius: 50%; height: 12.5px; width: 12.5px; transform: translateX(9px) translateY(-18px);"},"children":[]}]},{"type":"element","tag":"div","props":{"style":"margin-left: 8px;"},"children":[{"type":"text","value":" "},{"type":"element","tag":"div","props":{"style":" background-color: #F4F4F4; border-radius: 50%; flex-grow: 0; height: 20px; width: 20px;"},"children":[]},{"type":"text","value":" "},{"type":"element","tag":"div","props":{"style":" width: 0; height: 0; border-top: 2px solid transparent; border-left: 6px solid #f4f4f4; border-bottom: 2px solid transparent; transform: translateX(16px) translateY(-4px) rotate(30deg)"},"children":[]}]},{"type":"element","tag":"div","props":{"style":"margin-left: auto;"},"children":[{"type":"text","value":" "},{"type":"element","tag":"div","props":{"style":" width: 0px; border-top: 8px solid #F4F4F4; border-right: 8px solid transparent; transform: translateY(16px);"},"children":[]},{"type":"text","value":" "},{"type":"element","tag":"div","props":{"style":" background-color: #F4F4F4; flex-grow: 0; height: 12px; width: 16px; transform: translateY(-4px);"},"children":[]},{"type":"text","value":" "},{"type":"element","tag":"div","props":{"style":" width: 0; height: 0; border-top: 8px solid #F4F4F4; border-left: 8px solid transparent; transform: translateY(-4px) translateX(8px);"},"children":[]}]}]},{"type":"text","value":" "},{"type":"element","tag":"div","props":{"style":"display: flex; flex-direction: column; flex-grow: 1; justify-content: center; margin-bottom: 24px;"},"children":[{"type":"text","value":" "},{"type":"element","tag":"div","props":{"style":" background-color: #F4F4F4; border-radius: 4px; flex-grow: 0; height: 14px; margin-bottom: 6px; width: 224px;"},"children":[]},{"type":"text","value":" "},{"type":"element","tag":"div","props":{"style":" background-color: #F4F4F4; border-radius: 4px; flex-grow: 0; height: 14px; width: 144px;"},"children":[]}]}]},{"type":"element","tag":"p","props":{"style":" color:#c9c8cd; font-family:Arial,sans-serif; font-size:14px; line-height:17px; margin-bottom:0; margin-top:8px; overflow:hidden; padding:8px 0 7px; text-align:center; text-overflow:ellipsis; white-space:nowrap;"},"children":[{"type":"element","tag":"a","props":{"href":"https://www.instagram.com/p/88DiuyPmdl/?utm_source=ig_embed&utm_campaign=loading","style":" color:#c9c8cd; font-family:Arial,sans-serif; font-size:14px; font-style:normal; font-weight:normal; line-height:17px; text-decoration:none;","target":"_blank"},"children":[{"type":"text","value":"A post shared by Viviana Demicco (@vivianademicco)"}]}]}]}]},{"type":"element","tag":"h2","props":{"id":"tedx-18-ottobre-milano"},"children":[{"type":"text","value":"TEDx "},{"type":"element","tag":"small","props":{},"children":[{"type":"text","value":"(18 Ottobre, Milano)"}]}]},{"type":"element","tag":"p","props":{},"children":[{"type":"text","value":"Gli "},{"type":"element","tag":"a","props":{"href":"www.tedxmilano.it"},"children":[{"type":"text","value":"eventi "},{"type":"element","tag":"strong","props":{},"children":[{"type":"text","value":"TED"}]},{"type":"text","value":" indipendenti"}]},{"type":"text","value":" tornano a Milano!\nQuesta volta non mi sono fatto trovare impreparato e ho già comprato il biglietto. E per prepararmi mi sto guardando la registrazione dell'edizione precedente:"}]},{"type":"element","tag":"iframe","props":{"loading":"lazy","className":["w-full"],"height":515,"src":"https://www.youtube.com/embed/ZbPR7lkZyTQ?list=PLsRNoUx8w3rPflea6YPxnaw-iUpuqEwvf","frameBorder":"0","allowFullScreen":true},"children":[]},{"type":"element","tag":"h2","props":{"id":"comics-games-28-ottobre-1-novembre-lucca"},"children":[{"type":"text","value":"Comics & Games "},{"type":"element","tag":"small","props":{},"children":[{"type":"text","value":"(28 Ottobre - 1 Novembre, Lucca)"}]}]},{"type":"element","tag":"p","props":{},"children":[{"type":"text","value":"Il mio gran finale di questa maratona di eventi autunnali è l'ormai mitica manifestazione "},{"type":"element","tag":"strong","props":{},"children":[{"type":"element","tag":"a","props":{"href":"http://www.luccacomicsandgames.com/it/2016/home/","rel":["nofollow"]},"children":[{"type":"text","value":"Lucca Comics & Games"}]}]},{"type":"text","value":", che non ha bisogno di presentazioni. Purtroppo l'anno scorso l'ho dovuta saltare quindi quest'anno ho un altro buon motivo per non perdermela."}]},{"type":"element","tag":"p","props":{},"children":[{"type":"text","value":"Negli ultimi anni i giorni del Lucca Comics sono stati anche molto caldi e soleggiati per essere gli inizi di Novembre, ma indipendentemente dal clima niente è più eccezionale di un borgo come quello di Lucca invaso dai cosplayer più fantasiosi e curiosi di fumetti & dintorni da tutta europa!"}]},{"type":"element","tag":"blockquote","props":{"className":["instagram-media"],"dataInstgrmCaptioned":"","dataInstgrmPermalink":"https://www.instagram.com/p/BKVuoPJA4kP/?utm_source=ig_embed&utm_campaign=loading","dataInstgrmVersion":"14","style":" background:#FFF; border:0; border-radius:3px; box-shadow:0 0 1px 0 rgba(0,0,0,0.5),0 1px 10px 0 rgba(0,0,0,0.15); margin: 1px; max-width:540px; min-width:326px; padding:0; width:99.375%; width:-webkit-calc(100% - 2px); width:calc(100% - 2px);"},"children":[{"type":"element","tag":"div","props":{"style":"padding:16px;"},"children":[{"type":"text","value":" "},{"type":"element","tag":"a","props":{"href":"https://www.instagram.com/p/BKVuoPJA4kP/?utm_source=ig_embed&utm_campaign=loading","style":" background:#FFFFFF; line-height:0; padding:0 0; text-align:center; text-decoration:none; width:100%;","target":"_blank"},"children":[{"type":"text","value":" "},{"type":"element","tag":"div","props":{"style":" display: flex; flex-direction: row; align-items: center;"},"children":[{"type":"text","value":" "},{"type":"element","tag":"div","props":{"style":"background-color: #F4F4F4; border-radius: 50%; flex-grow: 0; height: 40px; margin-right: 14px; width: 40px;"},"children":[]},{"type":"text","value":" "},{"type":"element","tag":"div","props":{"style":"display: flex; flex-direction: column; flex-grow: 1; justify-content: center;"},"children":[{"type":"text","value":" "},{"type":"element","tag":"div","props":{"style":" background-color: #F4F4F4; border-radius: 4px; flex-grow: 0; height: 14px; margin-bottom: 6px; width: 100px;"},"children":[]},{"type":"text","value":" "},{"type":"element","tag":"div","props":{"style":" background-color: #F4F4F4; border-radius: 4px; flex-grow: 0; height: 14px; width: 60px;"},"children":[]}]}]},{"type":"element","tag":"div","props":{"style":"padding: 19% 0;"},"children":[]},{"type":"text","value":" "},{"type":"element","tag":"div","props":{"style":"display:block; height:50px; margin:0 auto 12px; width:50px;"},"children":[{"type":"element","tag":"svg","props":{"width":"50px","height":"50px","viewBox":"0 0 60 60","version":"1.1","xmlns":"https://www.w3.org/2000/svg","xmlnsXLink":"https://www.w3.org/1999/xlink"},"children":[{"type":"element","tag":"g","props":{"stroke":"none","strokeWidth":"1","fill":"none","fillRule":"evenodd"},"children":[{"type":"element","tag":"g","props":{"transform":"translate(-511.000000, -20.000000)","fill":"#000000"},"children":[{"type":"element","tag":"g","props":{},"children":[{"type":"element","tag":"path","props":{"d":"M556.869,30.41 C554.814,30.41 553.148,32.076 553.148,34.131 C553.148,36.186 554.814,37.852 556.869,37.852 C558.924,37.852 560.59,36.186 560.59,34.131 C560.59,32.076 558.924,30.41 556.869,30.41 M541,60.657 C535.114,60.657 530.342,55.887 530.342,50 C530.342,44.114 535.114,39.342 541,39.342 C546.887,39.342 551.658,44.114 551.658,50 C551.658,55.887 546.887,60.657 541,60.657 M541,33.886 C532.1,33.886 524.886,41.1 524.886,50 C524.886,58.899 532.1,66.113 541,66.113 C549.9,66.113 557.115,58.899 557.115,50 C557.115,41.1 549.9,33.886 541,33.886 M565.378,62.101 C565.244,65.022 564.756,66.606 564.346,67.663 C563.803,69.06 563.154,70.057 562.106,71.106 C561.058,72.155 560.06,72.803 558.662,73.347 C557.607,73.757 556.021,74.244 553.102,74.378 C549.944,74.521 548.997,74.552 541,74.552 C533.003,74.552 532.056,74.521 528.898,74.378 C525.979,74.244 524.393,73.757 523.338,73.347 C521.94,72.803 520.942,72.155 519.894,71.106 C518.846,70.057 518.197,69.06 517.654,67.663 C517.244,66.606 516.755,65.022 516.623,62.101 C516.479,58.943 516.448,57.996 516.448,50 C516.448,42.003 516.479,41.056 516.623,37.899 C516.755,34.978 517.244,33.391 517.654,32.338 C518.197,30.938 518.846,29.942 519.894,28.894 C520.942,27.846 521.94,27.196 523.338,26.654 C524.393,26.244 525.979,25.756 528.898,25.623 C532.057,25.479 533.004,25.448 541,25.448 C548.997,25.448 549.943,25.479 553.102,25.623 C556.021,25.756 557.607,26.244 558.662,26.654 C560.06,27.196 561.058,27.846 562.106,28.894 C563.154,29.942 563.803,30.938 564.346,32.338 C564.756,33.391 565.244,34.978 565.378,37.899 C565.522,41.056 565.552,42.003 565.552,50 C565.552,57.996 565.522,58.943 565.378,62.101 M570.82,37.631 C570.674,34.438 570.167,32.258 569.425,30.349 C568.659,28.377 567.633,26.702 565.965,25.035 C564.297,23.368 562.623,22.342 560.652,21.575 C558.743,20.834 556.562,20.326 553.369,20.18 C550.169,20.033 549.148,20 541,20 C532.853,20 531.831,20.033 528.631,20.18 C525.438,20.326 523.257,20.834 521.349,21.575 C519.376,22.342 517.703,23.368 516.035,25.035 C514.368,26.702 513.342,28.377 512.574,30.349 C511.834,32.258 511.326,34.438 511.181,37.631 C511.035,40.831 511,41.851 511,50 C511,58.147 511.035,59.17 511.181,62.369 C511.326,65.562 511.834,67.743 512.574,69.651 C513.342,71.625 514.368,73.296 516.035,74.965 C517.703,76.634 519.376,77.658 521.349,78.425 C523.257,79.167 525.438,79.673 528.631,79.82 C531.831,79.965 532.853,80.001 541,80.001 C549.148,80.001 550.169,79.965 553.369,79.82 C556.562,79.673 558.743,79.167 560.652,78.425 C562.623,77.658 564.297,76.634 565.965,74.965 C567.633,73.296 568.659,71.625 569.425,69.651 C570.167,67.743 570.674,65.562 570.82,62.369 C570.966,59.17 571,58.147 571,50 C571,41.851 570.966,40.831 570.82,37.631"},"children":[]}]}]}]}]}]},{"type":"element","tag":"div","props":{"style":"padding-top: 8px;"},"children":[{"type":"text","value":" "},{"type":"element","tag":"div","props":{"style":" color:#3897f0; font-family:Arial,sans-serif; font-size:14px; font-style:normal; font-weight:550; line-height:18px;"},"children":[{"type":"text","value":"View this post on Instagram"}]}]},{"type":"element","tag":"div","props":{"style":"padding: 12.5% 0;"},"children":[]},{"type":"text","value":" "},{"type":"element","tag":"div","props":{"style":"display: flex; flex-direction: row; margin-bottom: 14px; align-items: center;"},"children":[{"type":"element","tag":"div","props":{},"children":[{"type":"text","value":" "},{"type":"element","tag":"div","props":{"style":"background-color: #F4F4F4; border-radius: 50%; height: 12.5px; width: 12.5px; transform: translateX(0px) translateY(7px);"},"children":[]},{"type":"text","value":" "},{"type":"element","tag":"div","props":{"style":"background-color: #F4F4F4; height: 12.5px; transform: rotate(-45deg) translateX(3px) translateY(1px); width: 12.5px; flex-grow: 0; margin-right: 14px; margin-left: 2px;"},"children":[]},{"type":"text","value":" "},{"type":"element","tag":"div","props":{"style":"background-color: #F4F4F4; border-radius: 50%; height: 12.5px; width: 12.5px; transform: translateX(9px) translateY(-18px);"},"children":[]}]},{"type":"element","tag":"div","props":{"style":"margin-left: 8px;"},"children":[{"type":"text","value":" "},{"type":"element","tag":"div","props":{"style":" background-color: #F4F4F4; border-radius: 50%; flex-grow: 0; height: 20px; width: 20px;"},"children":[]},{"type":"text","value":" "},{"type":"element","tag":"div","props":{"style":" width: 0; height: 0; border-top: 2px solid transparent; border-left: 6px solid #f4f4f4; border-bottom: 2px solid transparent; transform: translateX(16px) translateY(-4px) rotate(30deg)"},"children":[]}]},{"type":"element","tag":"div","props":{"style":"margin-left: auto;"},"children":[{"type":"text","value":" "},{"type":"element","tag":"div","props":{"style":" width: 0px; border-top: 8px solid #F4F4F4; border-right: 8px solid transparent; transform: translateY(16px);"},"children":[]},{"type":"text","value":" "},{"type":"element","tag":"div","props":{"style":" background-color: #F4F4F4; flex-grow: 0; height: 12px; width: 16px; transform: translateY(-4px);"},"children":[]},{"type":"text","value":" "},{"type":"element","tag":"div","props":{"style":" width: 0; height: 0; border-top: 8px solid #F4F4F4; border-left: 8px solid transparent; transform: translateY(-4px) translateX(8px);"},"children":[]}]}]},{"type":"text","value":" "},{"type":"element","tag":"div","props":{"style":"display: flex; flex-direction: column; flex-grow: 1; justify-content: center; margin-bottom: 24px;"},"children":[{"type":"text","value":" "},{"type":"element","tag":"div","props":{"style":" background-color: #F4F4F4; border-radius: 4px; flex-grow: 0; height: 14px; margin-bottom: 6px; width: 224px;"},"children":[]},{"type":"text","value":" "},{"type":"element","tag":"div","props":{"style":" background-color: #F4F4F4; border-radius: 4px; flex-grow: 0; height: 14px; width: 144px;"},"children":[]}]}]},{"type":"element","tag":"p","props":{"style":" color:#c9c8cd; font-family:Arial,sans-serif; font-size:14px; line-height:17px; margin-bottom:0; margin-top:8px; overflow:hidden; padding:8px 0 7px; text-align:center; text-overflow:ellipsis; white-space:nowrap;"},"children":[{"type":"element","tag":"a","props":{"href":"https://www.instagram.com/p/BKVuoPJA4kP/?utm_source=ig_embed&utm_campaign=loading","style":" color:#c9c8cd; font-family:Arial,sans-serif; font-size:14px; font-style:normal; font-weight:normal; line-height:17px; text-decoration:none;","target":"_blank"},"children":[{"type":"text","value":"A post shared by Lucca Comics & Games (@luccacomicsandgames)"}]}]}]}]}],"toc":{"title":"","searchDepth":2,"depth":2,"links":[{"id":"festa-del-ticino-10-11-settembre-pavia","depth":2,"text":"Festa del Ticino (10-11 Settembre, Pavia)"},{"id":"autunno-pavese-23-26-settembre-pavia","depth":2,"text":"Autunno Pavese (23-26 Settembre, Pavia)"},{"id":"radiant-1-2-ottobre-novegro","depth":2,"text":"Radiant (1-2 Ottobre, Novegro)"},{"id":"birrart-13-16-ottobre-casteggio","depth":2,"text":"BirrArt (13-16 Ottobre, Casteggio)"},{"id":"games-week-14-16-ottobre-milano","depth":2,"text":"Games Week (14-16 Ottobre, Milano)"},{"id":"next-vintage-14-17-ottobre-belgioioso","depth":2,"text":"Next Vintage (14-17 Ottobre, Belgioioso)"},{"id":"tedx-18-ottobre-milano","depth":2,"text":"TEDx (18 Ottobre, Milano)"},{"id":"comics-games-28-ottobre-1-novembre-lucca","depth":2,"text":"Comics & Games (28 Ottobre - 1 Novembre, Lucca)"}]}},"_type":"markdown","_id":"content:estate-autunno-eventi.md","_source":"content","_file":"estate-autunno-eventi.md","_extension":"md"}